DynamicVirshService/DynamicVirshService.py
DynamicVirshService/__init__.py
DynamicVirshService/hassConfig.py
DynamicVirshService/mqttClient.py
DynamicVirshService/version.py
DynamicVirshService/virshClient.py
pyDynamicVirshService-1.0.0a22.dist-info/LICENSE
pyDynamicVirshService-1.0.0a22.dist-info/METADATA
pyDynamicVirshService-1.0.0a22.dist-info/WHEEL
pyDynamicVirshService-1.0.0a22.dist-info/top_level.txt
pyDynamicVirshService-1.0.0a22.dist-info/RECORD
